ip_to_country/__init__.py
ip_to_country/ip_to_country.py
ip_to_country/data/__init__.py
ip_to_country/data/country_info.pkl
ip_to_country/data/ipv4_ranges.pkl
ip_to_country/data/ipv6_ranges.pkl
ip_to_country-1.0.2.dist-info/licenses/LICENSE
ip_to_country-1.0.2.dist-info/METADATA
ip_to_country-1.0.2.dist-info/WHEEL
ip_to_country-1.0.2.dist-info/top_level.txt
ip_to_country-1.0.2.dist-info/RECORD
