Metadata-Version: 2.4
Name: ip-to-country
Version: 1.0.2
Summary: Convert IP addresses to countries using delegated registry data
Author: Pieter-Jan Coenen
Author-email: pieterjan.coenen@gmail.com
Requires-Python: >=3.6
License-File: LICENSE
Dynamic: author
Dynamic: author-email
Dynamic: description
Dynamic: description-content-type
Dynamic: license-file
Dynamic: requires-python
Dynamic: summary
